xmtp/__init__.py
xmtp/async_stream.py
xmtp/bindings.py
xmtp/client.py
xmtp/constants.py
xmtp/conversation.py
xmtp/conversations.py
xmtp/env.py
xmtp/errors.py
xmtp/identifiers.py
xmtp/messages.py
xmtp/preferences.py
xmtp/py.typed
xmtp/types.py
xmtp/utils.py
xmtp/signers/__init__.py
xmtp/signers/base.py
xmtp/signers/eoa.py
xmtp/signers/scw.py
xmtp-0.1.5.dist-info/licenses/LICENSE
xmtp_agent/__init__.py
xmtp_agent/agent.py
xmtp_agent/attachments.py
xmtp_agent/command_router.py
xmtp_agent/context.py
xmtp_agent/debug.py
xmtp_agent/errors.py
xmtp_agent/filters.py
xmtp_agent/middleware.py
xmtp_agent/name_resolver.py
xmtp_agent/py.typed
xmtp_agent/recipient_resolver.py
xmtp_agent/test_utils.py
xmtp_agent/user.py
xmtp_content_type_group_updated/__init__.py
xmtp_content_type_group_updated/py.typed
xmtp_content_type_markdown/__init__.py
xmtp_content_type_markdown/py.typed
xmtp_content_type_primitives/__init__.py
xmtp_content_type_primitives/py.typed
xmtp_content_type_reaction/__init__.py
xmtp_content_type_reaction/py.typed
xmtp_content_type_read_receipt/__init__.py
xmtp_content_type_read_receipt/py.typed
xmtp_content_type_remote_attachment/__init__.py
xmtp_content_type_remote_attachment/py.typed
xmtp_content_type_reply/__init__.py
xmtp_content_type_reply/py.typed
xmtp_content_type_text/__init__.py
xmtp_content_type_text/py.typed
xmtp_content_type_transaction_reference/__init__.py
xmtp_content_type_transaction_reference/py.typed
xmtp_content_type_wallet_send_calls/__init__.py
xmtp_content_type_wallet_send_calls/py.typed
xmtp-0.1.5.dist-info/METADATA
xmtp-0.1.5.dist-info/WHEEL
xmtp-0.1.5.dist-info/top_level.txt
xmtp-0.1.5.dist-info/RECORD
