Metadata-Version: 2.4
Name: xmtp
Version: 0.1.5
Summary: Unofficial Python SDK for the XMTP network.
Author: XMTP Python SDK contributors
License-Expression: Apache-2.0
Project-URL: Homepage, https://github.com/pierce403/xmtp-py
Project-URL: Source, https://github.com/pierce403/xmtp-py
Project-URL: Issues, https://github.com/pierce403/xmtp-py/issues
Project-URL: Documentation, https://github.com/pierce403/xmtp-py#readme
Keywords: xmtp,messaging,web3
Classifier: Development Status :: 3 - Alpha
Classifier: Intended Audience :: Developers
Classifier: Programming Language :: Python :: 3
Classifier: Programming Language :: Python :: 3 :: Only
Classifier: Programming Language :: Python :: 3.10
Classifier: Programming Language :: Python :: 3.11
Classifier: Programming Language :: Python :: 3.12
Classifier: Programming Language :: Python :: 3.13
Classifier: Typing :: Typed
Requires-Python: >=3.10
License-File: LICENSE
Requires-Dist: eth-account>=0.12
Requires-Dist: xmtp-bindings>=0.1.5
Provides-Extra: dev
Requires-Dist: pytest>=7; extra == "dev"
Requires-Dist: pytest-asyncio>=0.21; extra == "dev"
Requires-Dist: pytest-cov>=5; extra == "dev"
Requires-Dist: mypy>=1.7; extra == "dev"
Requires-Dist: ruff>=0.1; extra == "dev"
Requires-Dist: sphinx>=7; extra == "dev"
Requires-Dist: sphinx-autodoc-typehints>=1.24; extra == "dev"
Requires-Dist: build>=1.2; extra == "dev"
Requires-Dist: twine>=5; extra == "dev"
Dynamic: license-file
